sequence_detec/sequ.v
//sequence to be detected is "0110";
module seq_det (
    clk,a,reset,out
);
    input clk,a,reset;
    output reg out;
    parameter s0 = 0,s1=1,s2=2,s3=3;
    reg [0:1] PS,NS;
    always @(posedge clk or posedge reset)
    if(reset)
    PS <=0;
    else
    PS<=NS;
    always @(PS,a)
    case (PS)
        s0:begin
          out = a ? 0 :0;
          NS =a?s0:s1;  
        end 
        s1:begin
          out = a?0:0;
          NS =a?s2:s1;  
        end 
        s2:begin
          out = a?0:0;
          NS =a?s3:s1;  
        end 
        s3:begin
          out = a?0:1;
          NS =a?s0:s1;  
        end 
    endcase
endmodule

sequence_detec/sequ_tb.v
`include "sequ.v"
module test ;
reg clock,res,in;
wire o;
seq_det qw(clock,in,res,o);
initial begin
    $dumpfile("seq.vcd");
    $dumpvars(0,test);
    clock = 1'b0;
    res = 1'b1;
    # 15 res =1'b0;
end   
always #5 clock=~clock;
initial begin
    #12 in = 0;
    #10 in=0;
    #10 in =1;
    #10 in =1;
    
     #10 in = 0;
    #10 in=1;
    #10 in =1;
    #10 in =0;
    #10 in = 0;
    #10 in=1;
    #10 in =1;
    #10 in =0;
    #10 $finish;
end
endmodule

sequence_detec/seq.vcd
$date
	Mon Jul 03 14:02:51 2023
$end
$version
	Icarus Verilog
$end
$timescale
	1s
$end
$scope module test $end
$var wire 1 ! o $end
$var reg 1 " clock $end
$var reg 1 # in $end
$var reg 1 $ res $end
$scope module qw $end
$var wire 1 # a $end
$var wire 1 " clk $end
$var wire 1 $ reset $end
$var parameter 32 % s0 $end
$var parameter 32 & s1 $end
$var parameter 32 ' s2 $end
$var parameter 32 ( s3 $end
$var reg 2 ) NS [0:1] $end
$var reg 2 * PS [0:1] $end
$var reg 1 ! out $end
$upscope $end
$upscope $end
$enddefinitions $end
$comment Show the parameter values. $end
$dumpall
b11 (
b10 '
b1 &
b0 %
$end
#0
$dumpvars
b0 *
b0x )
1$
x#
0"
0!
$end
#5
1"
#10
0"
#12
b1 )
0#
#15
b1 *
1"
0$
#20
0"
#25
1"
#30
0"
#32
b10 )
1#
#35
b11 )
b10 *
1"
#40
0"
#45
b0 )
b11 *
1"
#50
0"
#52
b1 )
1!
0#
#55
0!
b1 *
1"
#60
0"
#62
b10 )
1#
#65
b11 )
b10 *
1"
#70
0"
#75
b0 )
b11 *
1"
#80
0"
#82
b1 )
1!
0#
#85
0!
b1 *
1"
#90
0"
#95
1"
#100
0"
#102
b10 )
1#
#105
b11 )
b10 *
1"
#110
0"
#115
b0 )
b11 *
1"
#120
0"
#122
b1 )
1!
0#
#125
0!
b1 *
1"
